TCGPR/TCGPR.py
TCGPR/TCGPRdata.py
TCGPR/TCGPRdata_r.py
TCGPR/TCGPRfeature.py
TCGPR/__init__.py
TCGPR-1.5.0.dist-info/METADATA
TCGPR-1.5.0.dist-info/WHEEL
TCGPR-1.5.0.dist-info/top_level.txt
TCGPR-1.5.0.dist-info/RECORD
