Metadata-Version: 2.1
Name: TCGPR
Version: 1.5.0
Summary: Tree-Classifier for gaussian process model (TCGPR) is a data preprocessing algorithm based on the Gaussian correlation among data.
Home-page: https://github.com/Bin-Cao/TCGPR
Author: CaoBin
Author-email: bcao@shu.edu.com
Maintainer: CaoBin
Maintainer-email: 17734910905@163.com
License: MIT License
Classifier: Development Status :: 3 - Alpha
Classifier: Intended Audience :: Developers
Classifier: Topic :: Software Development :: Build Tools
Classifier: License :: OSI Approved :: MIT License
Classifier: Programming Language :: Python :: 3
Requires-Python: >=3.7
Requires-Dist: scipy
Requires-Dist: sklearn
Requires-Dist: pandas
